pytest_info_collector/__init__.py
pytest_info_collector/_version.py
pytest_info_collector-0.3.dist-info/METADATA
pytest_info_collector-0.3.dist-info/WHEEL
pytest_info_collector-0.3.dist-info/entry_points.txt
pytest_info_collector-0.3.dist-info/top_level.txt
pytest_info_collector-0.3.dist-info/RECORD
